rubin/squarebot/__init__.py
rubin/squarebot/py.typed
rubin/squarebot/models/__init__.py
rubin/squarebot/models/kafka.py
rubin/squarebot/models/slack.py
rubin_squarebot-0.10.0.dist-info/LICENSE
rubin_squarebot-0.10.0.dist-info/METADATA
rubin_squarebot-0.10.0.dist-info/WHEEL
rubin_squarebot-0.10.0.dist-info/top_level.txt
rubin_squarebot-0.10.0.dist-info/RECORD
