Metadata-Version: 2.1
Name: rubin-squarebot
Version: 0.10.0
Summary: Client library for the Rubin Observatory Squarebot
License: The MIT License (MIT)
Project-URL: Homepage, https://github.com/lsst-sqre/squarebot
Project-URL: Source, https://github.com/lsst-sqre/squarebot
Keywords: rubin,lsst
Classifier: Development Status :: 4 - Beta
Classifier: License :: OSI Approved :: MIT License
Classifier: Programming Language :: Python
Classifier: Programming Language :: Python :: 3
Classifier: Programming Language :: Python :: 3.11
Classifier: Intended Audience :: Developers
Classifier: Natural Language :: English
Classifier: Operating System :: POSIX
Classifier: Typing :: Typed
Requires-Python: >=3.11
License-File: LICENSE
Requires-Dist: pydantic>=2
Requires-Dist: safir
Provides-Extra: dev
Requires-Dist: mypy; extra == "dev"
